{
  "script_version": "phase2a_v2_tag_diagnostics",
  "robot_id": "twin-scout-delta",
  "ground_truth": {
    "x_m": 4.31,
    "y_m": 3.66,
    "heading_deg": 180.0
  },
  "errors": {
    "position_error_m": 0.5026227974937968,
    "heading_error_deg": 8.250765435400979
  },
  "summary": {
    "estimate_ok": true,
    "tag_count": 8,
    "front_count": 7,
    "rear_count": 1,
    "tags_used": [
      38,
      39,
      40,
      41,
      42,
      43,
      44
    ]
  },
  "assets": {
    "status": "ok",
    "detail": "mobility assets ready",
    "site_name": "DemoRoom",
    "site_dir": "sitemap\\DemoRoom",
    "site_json_path": "sitemap\\DemoRoom\\site.json",
    "static_map_path": "sitemap\\DemoRoom\\restriction_map.npy",
    "tag_location_path": "sitemap\\DemoRoom\\tag_location.txt",
    "static_map_shape": [
      114,
      114
    ],
    "world_width_m": 11.4,
    "world_height_m": 11.4,
    "grid_resolution_m": 0.1,
    "tag_count": 58,
    "tag_map_key": "nms:mobility:tag_map_json"
  },
  "report": {
    "last_command": "mobility.report.location",
    "last_command_args": {},
    "last_command_received_ts": 1781596026.3645918,
    "last_command_finished_ts": 1781596035.6908956,
    "last_exec_status": "completed",
    "last_error_code": "",
    "last_error_detail": "",
    "last_location_result": {
      "ok": true,
      "capture_mode": "dual_camera",
      "camera_roles": [
        "front",
        "rear"
      ],
      "av_was_active": false,
      "av_restarted": false,
      "snapshots": {
        "front": "/tmp/location_front_1781596026466.jpg",
        "rear": "/tmp/location_rear_1781596031974.jpg"
      },
      "front": {
        "ok": true,
        "camera_role": "front",
        "snapshot": {
          "ok": true,
          "stage": "snapshot",
          "camera_role": "front",
          "snapshot_path": "/tmp/location_front_1781596026466.jpg",
          "video_dev": "/dev/v4l/by-id/usb-webcamvendor_webcamproduct_YGR80PU1200.23071717-video-index0",
          "width": 1280,
          "height": 720,
          "attempt": 1,
          "detail": {
            "ok": true,
            "error": "",
            "output_path": "/tmp/location_front_1781596026466.jpg",
            "width": 1280,
            "height": 720
          },
          "error": ""
        },
        "apriltag": {
          "ok": true,
          "error": "",
          "image_path": "/tmp/location_front_1781596026466.jpg",
          "camera_role": "front",
          "image_width": 1280,
          "image_height": 720,
          "count": 7,
          "tags": [
            {
              "id": 38,
              "library_pose": {
                "distance_m": 2.6743,
                "angle_deg": 35.995,
                "yaw_deg": -56.7053
              },
              "calibrated_pose": {
                "distance_m": 2.6217,
                "angle_deg": 37.3636,
                "yaw_deg": -52.5615
              }
            },
            {
              "id": 39,
              "library_pose": {
                "distance_m": 3.3906,
                "angle_deg": 27.7288,
                "yaw_deg": -61.9055
              },
              "calibrated_pose": {
                "distance_m": 3.3268,
                "angle_deg": 28.5328,
                "yaw_deg": -57.3082
              }
            },
            {
              "id": 40,
              "library_pose": {
                "distance_m": 3.3886,
                "angle_deg": 17.7886,
                "yaw_deg": -23.363
              },
              "calibrated_pose": {
                "distance_m": 3.3249,
                "angle_deg": 17.9138,
                "yaw_deg": -22.1266
              }
            },
            {
              "id": 41,
              "library_pose": {
                "distance_m": 3.0781,
                "angle_deg": 0.2161,
                "yaw_deg": -0.0
              },
              "calibrated_pose": {
                "distance_m": 3.0192,
                "angle_deg": -0.8589,
                "yaw_deg": -0.8009
              }
            },
            {
              "id": 42,
              "library_pose": {
                "distance_m": 3.3609,
                "angle_deg": -16.8037,
                "yaw_deg": -21.9824
              },
              "calibrated_pose": {
                "distance_m": 3.2976,
                "angle_deg": -19.0412,
                "yaw_deg": -20.8664
              }
            },
            {
              "id": 43,
              "library_pose": {
                "distance_m": 4.0981,
                "angle_deg": -29.3682,
                "yaw_deg": -42.173
              },
              "calibrated_pose": {
                "distance_m": 4.0233,
                "angle_deg": -32.4639,
                "yaw_deg": -39.2964
              }
            },
            {
              "id": 44,
              "library_pose": {
                "distance_m": 5.1853,
                "angle_deg": -36.4128,
                "yaw_deg": -56.6607
              },
              "calibrated_pose": {
                "distance_m": 5.0937,
                "angle_deg": -39.9896,
                "yaw_deg": -52.5208
              }
            }
          ],
          "camera_params": {
            "fx": 857.2,
            "fy": 851.8,
            "cx": 640.0,
            "cy": 360.0,
            "tag_size_m": 0.1
          },
          "snapshot_path": "/tmp/location_front_1781596026466.jpg"
        },
        "snapshot_path": "/tmp/location_front_1781596026466.jpg",
        "tags": [
          {
            "id": 38,
            "library_pose": {
              "distance_m": 2.6743,
              "angle_deg": 35.995,
              "yaw_deg": -56.7053
            },
            "calibrated_pose": {
              "distance_m": 2.6217,
              "angle_deg": 37.3636,
              "yaw_deg": -52.5615
            }
          },
          {
            "id": 39,
            "library_pose": {
              "distance_m": 3.3906,
              "angle_deg": 27.7288,
              "yaw_deg": -61.9055
            },
            "calibrated_pose": {
              "distance_m": 3.3268,
              "angle_deg": 28.5328,
              "yaw_deg": -57.3082
            }
          },
          {
            "id": 40,
            "library_pose": {
              "distance_m": 3.3886,
              "angle_deg": 17.7886,
              "yaw_deg": -23.363
            },
            "calibrated_pose": {
              "distance_m": 3.3249,
              "angle_deg": 17.9138,
              "yaw_deg": -22.1266
            }
          },
          {
            "id": 41,
            "library_pose": {
              "distance_m": 3.0781,
              "angle_deg": 0.2161,
              "yaw_deg": -0.0
            },
            "calibrated_pose": {
              "distance_m": 3.0192,
              "angle_deg": -0.8589,
              "yaw_deg": -0.8009
            }
          },
          {
            "id": 42,
            "library_pose": {
              "distance_m": 3.3609,
              "angle_deg": -16.8037,
              "yaw_deg": -21.9824
            },
            "calibrated_pose": {
              "distance_m": 3.2976,
              "angle_deg": -19.0412,
              "yaw_deg": -20.8664
            }
          },
          {
            "id": 43,
            "library_pose": {
              "distance_m": 4.0981,
              "angle_deg": -29.3682,
              "yaw_deg": -42.173
            },
            "calibrated_pose": {
              "distance_m": 4.0233,
              "angle_deg": -32.4639,
              "yaw_deg": -39.2964
            }
          },
          {
            "id": 44,
            "library_pose": {
              "distance_m": 5.1853,
              "angle_deg": -36.4128,
              "yaw_deg": -56.6607
            },
            "calibrated_pose": {
              "distance_m": 5.0937,
              "angle_deg": -39.9896,
              "yaw_deg": -52.5208
            }
          }
        ],
        "count": 7,
        "error": ""
      },
      "rear": {
        "ok": true,
        "camera_role": "rear",
        "snapshot": {
          "ok": true,
          "stage": "snapshot",
          "camera_role": "rear",
          "snapshot_path": "/tmp/location_rear_1781596031974.jpg",
          "video_dev": "/dev/v4l/by-id/usb-046d_C270_HD_WEBCAM_200901010001-video-index0",
          "width": 640,
          "height": 480,
          "attempt": 1,
          "detail": {
            "ok": true,
            "error": "",
            "output_path": "/tmp/location_rear_1781596031974.jpg",
            "width": 640,
            "height": 480
          },
          "error": ""
        },
        "apriltag": {
          "ok": true,
          "error": "",
          "image_path": "/tmp/location_rear_1781596031974.jpg",
          "camera_role": "rear",
          "image_width": 640,
          "image_height": 480,
          "count": 1,
          "tags": [
            {
              "id": 59,
              "library_pose": {
                "distance_m": 0.6011,
                "angle_deg": -6.9356,
                "yaw_deg": 0.0
              },
              "calibrated_pose": {
                "distance_m": 0.7504,
                "angle_deg": -5.5679,
                "yaw_deg": 0.584
              }
            }
          ],
          "camera_params": {
            "fx": 554.0,
            "fy": 554.0,
            "cx": 320.0,
            "cy": 240.0,
            "tag_size_m": 0.1
          },
          "snapshot_path": "/tmp/location_rear_1781596031974.jpg"
        },
        "snapshot_path": "/tmp/location_rear_1781596031974.jpg",
        "tags": [
          {
            "id": 59,
            "library_pose": {
              "distance_m": 0.6011,
              "angle_deg": -6.9356,
              "yaw_deg": 0.0
            },
            "calibrated_pose": {
              "distance_m": 0.7504,
              "angle_deg": -5.5679,
              "yaw_deg": 0.584
            }
          }
        ],
        "count": 1,
        "error": ""
      },
      "apriltag": {
        "ok": true,
        "capture_mode": "dual_camera",
        "count": 8,
        "unique_count": 8,
        "unique_tag_ids": [
          38,
          39,
          40,
          41,
          42,
          43,
          44,
          59
        ],
        "tags": [
          {
            "id": 38,
            "library_pose": {
              "distance_m": 2.6743,
              "angle_deg": 35.995,
              "yaw_deg": -56.7053
            },
            "calibrated_pose": {
              "distance_m": 2.6217,
              "angle_deg": 37.3636,
              "yaw_deg": -52.5615
            },
            "camera_role": "front",
            "snapshot_path": "/tmp/location_front_1781596026466.jpg"
          },
          {
            "id": 39,
            "library_pose": {
              "distance_m": 3.3906,
              "angle_deg": 27.7288,
              "yaw_deg": -61.9055
            },
            "calibrated_pose": {
              "distance_m": 3.3268,
              "angle_deg": 28.5328,
              "yaw_deg": -57.3082
            },
            "camera_role": "front",
            "snapshot_path": "/tmp/location_front_1781596026466.jpg"
          },
          {
            "id": 40,
            "library_pose": {
              "distance_m": 3.3886,
              "angle_deg": 17.7886,
              "yaw_deg": -23.363
            },
            "calibrated_pose": {
              "distance_m": 3.3249,
              "angle_deg": 17.9138,
              "yaw_deg": -22.1266
            },
            "camera_role": "front",
            "snapshot_path": "/tmp/location_front_1781596026466.jpg"
          },
          {
            "id": 41,
            "library_pose": {
              "distance_m": 3.0781,
              "angle_deg": 0.2161,
              "yaw_deg": -0.0
            },
            "calibrated_pose": {
              "distance_m": 3.0192,
              "angle_deg": -0.8589,
              "yaw_deg": -0.8009
            },
            "camera_role": "front",
            "snapshot_path": "/tmp/location_front_1781596026466.jpg"
          },
          {
            "id": 42,
            "library_pose": {
              "distance_m": 3.3609,
              "angle_deg": -16.8037,
              "yaw_deg": -21.9824
            },
            "calibrated_pose": {
              "distance_m": 3.2976,
              "angle_deg": -19.0412,
              "yaw_deg": -20.8664
            },
            "camera_role": "front",
            "snapshot_path": "/tmp/location_front_1781596026466.jpg"
          },
          {
            "id": 43,
            "library_pose": {
              "distance_m": 4.0981,
              "angle_deg": -29.3682,
              "yaw_deg": -42.173
            },
            "calibrated_pose": {
              "distance_m": 4.0233,
              "angle_deg": -32.4639,
              "yaw_deg": -39.2964
            },
            "camera_role": "front",
            "snapshot_path": "/tmp/location_front_1781596026466.jpg"
          },
          {
            "id": 44,
            "library_pose": {
              "distance_m": 5.1853,
              "angle_deg": -36.4128,
              "yaw_deg": -56.6607
            },
            "calibrated_pose": {
              "distance_m": 5.0937,
              "angle_deg": -39.9896,
              "yaw_deg": -52.5208
            },
            "camera_role": "front",
            "snapshot_path": "/tmp/location_front_1781596026466.jpg"
          },
          {
            "id": 59,
            "library_pose": {
              "distance_m": 0.6011,
              "angle_deg": -6.9356,
              "yaw_deg": 0.0
            },
            "calibrated_pose": {
              "distance_m": 0.7504,
              "angle_deg": -5.5679,
              "yaw_deg": 0.584
            },
            "camera_role": "rear",
            "snapshot_path": "/tmp/location_rear_1781596031974.jpg"
          }
        ],
        "front": {
          "ok": true,
          "error": "",
          "image_path": "/tmp/location_front_1781596026466.jpg",
          "camera_role": "front",
          "image_width": 1280,
          "image_height": 720,
          "count": 7,
          "tags": [
            {
              "id": 38,
              "library_pose": {
                "distance_m": 2.6743,
                "angle_deg": 35.995,
                "yaw_deg": -56.7053
              },
              "calibrated_pose": {
                "distance_m": 2.6217,
                "angle_deg": 37.3636,
                "yaw_deg": -52.5615
              }
            },
            {
              "id": 39,
              "library_pose": {
                "distance_m": 3.3906,
                "angle_deg": 27.7288,
                "yaw_deg": -61.9055
              },
              "calibrated_pose": {
                "distance_m": 3.3268,
                "angle_deg": 28.5328,
                "yaw_deg": -57.3082
              }
            },
            {
              "id": 40,
              "library_pose": {
                "distance_m": 3.3886,
                "angle_deg": 17.7886,
                "yaw_deg": -23.363
              },
              "calibrated_pose": {
                "distance_m": 3.3249,
                "angle_deg": 17.9138,
                "yaw_deg": -22.1266
              }
            },
            {
              "id": 41,
              "library_pose": {
                "distance_m": 3.0781,
                "angle_deg": 0.2161,
                "yaw_deg": -0.0
              },
              "calibrated_pose": {
                "distance_m": 3.0192,
                "angle_deg": -0.8589,
                "yaw_deg": -0.8009
              }
            },
            {
              "id": 42,
              "library_pose": {
                "distance_m": 3.3609,
                "angle_deg": -16.8037,
                "yaw_deg": -21.9824
              },
              "calibrated_pose": {
                "distance_m": 3.2976,
                "angle_deg": -19.0412,
                "yaw_deg": -20.8664
              }
            },
            {
              "id": 43,
              "library_pose": {
                "distance_m": 4.0981,
                "angle_deg": -29.3682,
                "yaw_deg": -42.173
              },
              "calibrated_pose": {
                "distance_m": 4.0233,
                "angle_deg": -32.4639,
                "yaw_deg": -39.2964
              }
            },
            {
              "id": 44,
              "library_pose": {
                "distance_m": 5.1853,
                "angle_deg": -36.4128,
                "yaw_deg": -56.6607
              },
              "calibrated_pose": {
                "distance_m": 5.0937,
                "angle_deg": -39.9896,
                "yaw_deg": -52.5208
              }
            }
          ],
          "camera_params": {
            "fx": 857.2,
            "fy": 851.8,
            "cx": 640.0,
            "cy": 360.0,
            "tag_size_m": 0.1
          },
          "snapshot_path": "/tmp/location_front_1781596026466.jpg"
        },
        "rear": {
          "ok": true,
          "error": "",
          "image_path": "/tmp/location_rear_1781596031974.jpg",
          "camera_role": "rear",
          "image_width": 640,
          "image_height": 480,
          "count": 1,
          "tags": [
            {
              "id": 59,
              "library_pose": {
                "distance_m": 0.6011,
                "angle_deg": -6.9356,
                "yaw_deg": 0.0
              },
              "calibrated_pose": {
                "distance_m": 0.7504,
                "angle_deg": -5.5679,
                "yaw_deg": 0.584
              }
            }
          ],
          "camera_params": {
            "fx": 554.0,
            "fy": 554.0,
            "cx": 320.0,
            "cy": 240.0,
            "tag_size_m": 0.1
          },
          "snapshot_path": "/tmp/location_rear_1781596031974.jpg"
        },
        "front_count": 7,
        "rear_count": 1
      },
      "error": ""
    }
  },
  "observations": [
    {
      "id": 38,
      "camera_role": "front",
      "camera_offset_deg": 0.0,
      "camera_forward_offset_m": 0.055,
      "distance_m": 2.6217,
      "angle_deg_cw": 37.3636,
      "yaw_deg": -52.5615,
      "bearing_robot_deg_ccw": -37.36359999999999,
      "snapshot_path": "/tmp/location_front_1781596026466.jpg"
    },
    {
      "id": 39,
      "camera_role": "front",
      "camera_offset_deg": 0.0,
      "camera_forward_offset_m": 0.055,
      "distance_m": 3.3268,
      "angle_deg_cw": 28.5328,
      "yaw_deg": -57.3082,
      "bearing_robot_deg_ccw": -28.53280000000001,
      "snapshot_path": "/tmp/location_front_1781596026466.jpg"
    },
    {
      "id": 40,
      "camera_role": "front",
      "camera_offset_deg": 0.0,
      "camera_forward_offset_m": 0.055,
      "distance_m": 3.3249,
      "angle_deg_cw": 17.9138,
      "yaw_deg": -22.1266,
      "bearing_robot_deg_ccw": -17.91380000000001,
      "snapshot_path": "/tmp/location_front_1781596026466.jpg"
    },
    {
      "id": 41,
      "camera_role": "front",
      "camera_offset_deg": 0.0,
      "camera_forward_offset_m": 0.055,
      "distance_m": 3.0192,
      "angle_deg_cw": -0.8589,
      "yaw_deg": -0.8009,
      "bearing_robot_deg_ccw": 0.8589000000000055,
      "snapshot_path": "/tmp/location_front_1781596026466.jpg"
    },
    {
      "id": 42,
      "camera_role": "front",
      "camera_offset_deg": 0.0,
      "camera_forward_offset_m": 0.055,
      "distance_m": 3.2976,
      "angle_deg_cw": -19.0412,
      "yaw_deg": -20.8664,
      "bearing_robot_deg_ccw": 19.041200000000003,
      "snapshot_path": "/tmp/location_front_1781596026466.jpg"
    },
    {
      "id": 43,
      "camera_role": "front",
      "camera_offset_deg": 0.0,
      "camera_forward_offset_m": 0.055,
      "distance_m": 4.0233,
      "angle_deg_cw": -32.4639,
      "yaw_deg": -39.2964,
      "bearing_robot_deg_ccw": 32.463899999999995,
      "snapshot_path": "/tmp/location_front_1781596026466.jpg"
    },
    {
      "id": 44,
      "camera_role": "front",
      "camera_offset_deg": 0.0,
      "camera_forward_offset_m": 0.055,
      "distance_m": 5.0937,
      "angle_deg_cw": -39.9896,
      "yaw_deg": -52.5208,
      "bearing_robot_deg_ccw": 39.989599999999996,
      "snapshot_path": "/tmp/location_front_1781596026466.jpg"
    },
    {
      "id": 59,
      "camera_role": "rear",
      "camera_offset_deg": 180.0,
      "camera_forward_offset_m": -0.055,
      "distance_m": 0.7504,
      "angle_deg_cw": -5.5679,
      "yaw_deg": 0.584,
      "bearing_robot_deg_ccw": -174.4321,
      "snapshot_path": "/tmp/location_rear_1781596031974.jpg"
    }
  ],
  "estimate": {
    "location_ok": true,
    "x_m": 4.370536394979239,
    "y_m": 4.158963948039744,
    "heading_deg": 188.25076543540098,
    "source": "apriltag",
    "tags_used": [
      38,
      39,
      40,
      41,
      42,
      43,
      44
    ],
    "tag_count": 7,
    "solver_stage": "best_effort_fusion",
    "updated_at": "2026-06-16-15:47:26",
    "detail": "5 soft outlier(s) kept in fusion",
    "candidates": [
      {
        "tag_id": 38,
        "camera_role": "front",
        "camera_offset_deg": 0.0,
        "camera_forward_offset_m": 0.055,
        "camera_x_m": 4.711646353292452,
        "camera_y_m": 3.6062436353619685,
        "x_m": 4.766646306297523,
        "y_m": 3.6061717365439105,
        "heading_deg": 179.92510000000004,
        "distance_m": 2.6217,
        "angle_deg_cw": 37.3636,
        "yaw_deg": -52.5615,
        "bearing_robot_deg_ccw": -37.36359999999999,
        "snapshot_path": "/tmp/location_front_1781596026466.jpg",
        "yaw_corrected_deg": -89.9251
      },
      {
        "tag_id": 39,
        "camera_role": "front",
        "camera_offset_deg": 0.0,
        "camera_forward_offset_m": 0.055,
        "camera_x_m": 4.469795260806633,
        "camera_y_m": 3.403129181725988,
        "x_m": 4.524650425458361,
        "y_m": 3.3991403333919803,
        "heading_deg": 175.841,
        "distance_m": 3.3268,
        "angle_deg_cw": 28.5328,
        "yaw_deg": -57.3082,
        "bearing_robot_deg_ccw": -28.53280000000001,
        "snapshot_path": "/tmp/location_front_1781596026466.jpg",
        "yaw_corrected_deg": -85.84100000000001
      },
      {
        "tag_id": 40,
        "camera_role": "front",
        "camera_offset_deg": 0.0,
        "camera_forward_offset_m": 0.055,
        "camera_x_m": 4.280033969269751,
        "camera_y_m": 5.852338116542183,
        "x_m": 4.322141475084445,
        "y_m": 5.88772113441892,
        "heading_deg": 220.0404,
        "distance_m": 3.3249,
        "angle_deg_cw": 17.9138,
        "yaw_deg": -22.1266,
        "bearing_robot_deg_ccw": -17.91380000000001,
        "snapshot_path": "/tmp/location_front_1781596026466.jpg",
        "yaw_corrected_deg": -40.0404
      },
      {
        "tag_id": 41,
        "camera_role": "front",
        "camera_offset_deg": 0.0,
        "camera_forward_offset_m": 0.055,
        "camera_x_m": 4.218905037953307,
        "camera_y_m": 3.6422020357345986,
        "x_m": 4.273905009773151,
        "y_m": 3.642146359740969,
        "heading_deg": 179.942,
        "distance_m": 3.0192,
        "angle_deg_cw": -0.8589,
        "yaw_deg": -0.8009,
        "bearing_robot_deg_ccw": 0.8589000000000055,
        "snapshot_path": "/tmp/location_front_1781596026466.jpg",
        "yaw_corrected_deg": 0.05800000000000005
      },
      {
        "tag_id": 42,
        "camera_role": "front",
        "camera_offset_deg": 0.0,
        "camera_forward_offset_m": 0.055,
        "camera_x_m": 4.301322009574737,
        "camera_y_m": 3.8245724470250013,
        "x_m": 4.356294105243249,
        "y_m": 3.82632421693342,
        "heading_deg": 181.8252,
        "distance_m": 3.2976,
        "angle_deg_cw": -19.0412,
        "yaw_deg": -20.8664,
        "bearing_robot_deg_ccw": 19.041200000000003,
        "snapshot_path": "/tmp/location_front_1781596026466.jpg",
        "yaw_corrected_deg": -1.8251999999999988
      },
      {
        "tag_id": 43,
        "camera_role": "front",
        "camera_offset_deg": 0.0,
        "camera_forward_offset_m": 0.055,
        "camera_x_m": 4.333551422880978,
        "camera_y_m": 4.178085639666735,
        "x_m": 4.388160823102464,
        "y_m": 4.184628835174258,
        "heading_deg": 186.83249999999998,
        "distance_m": 4.0233,
        "angle_deg_cw": -32.4639,
        "yaw_deg": -39.2964,
        "bearing_robot_deg_ccw": 32.463899999999995,
        "snapshot_path": "/tmp/location_front_1781596026466.jpg",
        "yaw_corrected_deg": -6.832499999999996
      },
      {
        "tag_id": 44,
        "camera_role": "front",
        "camera_offset_deg": 0.0,
        "camera_forward_offset_m": 0.055,
        "camera_x_m": 4.31938085081645,
        "camera_y_m": 4.6522293393117,
        "x_m": 4.373070640913211,
        "y_m": 4.66416275623083,
        "heading_deg": 192.5312,
        "distance_m": 5.0937,
        "angle_deg_cw": -39.9896,
        "yaw_deg": -52.5208,
        "bearing_robot_deg_ccw": 39.989599999999996,
        "snapshot_path": "/tmp/location_front_1781596026466.jpg",
        "yaw_corrected_deg": -12.531199999999998
      }
    ],
    "used_candidates": [
      {
        "tag_id": 38,
        "camera_role": "front",
        "camera_offset_deg": 0.0,
        "camera_forward_offset_m": 0.055,
        "camera_x_m": 4.711646353292452,
        "camera_y_m": 3.6062436353619685,
        "x_m": 4.766646306297523,
        "y_m": 3.6061717365439105,
        "heading_deg": 179.92510000000004,
        "distance_m": 2.6217,
        "angle_deg_cw": 37.3636,
        "yaw_deg": -52.5615,
        "bearing_robot_deg_ccw": -37.36359999999999,
        "snapshot_path": "/tmp/location_front_1781596026466.jpg",
        "yaw_corrected_deg": -89.9251,
        "position_residual_m": 0.6800605053486289,
        "heading_residual_deg": 8.325665435400936,
        "weight": 0.10480564091785488
      },
      {
        "tag_id": 39,
        "camera_role": "front",
        "camera_offset_deg": 0.0,
        "camera_forward_offset_m": 0.055,
        "camera_x_m": 4.469795260806633,
        "camera_y_m": 3.403129181725988,
        "x_m": 4.524650425458361,
        "y_m": 3.3991403333919803,
        "heading_deg": 175.841,
        "distance_m": 3.3268,
        "angle_deg_cw": 28.5328,
        "yaw_deg": -57.3082,
        "bearing_robot_deg_ccw": -28.53280000000001,
        "snapshot_path": "/tmp/location_front_1781596026466.jpg",
        "yaw_corrected_deg": -85.84100000000001,
        "position_residual_m": 0.7752954661075431,
        "heading_residual_deg": 12.40976543540097,
        "weight": 0.2006290884755269
      },
      {
        "tag_id": 40,
        "camera_role": "front",
        "camera_offset_deg": 0.0,
        "camera_forward_offset_m": 0.055,
        "camera_x_m": 4.280033969269751,
        "camera_y_m": 5.852338116542183,
        "x_m": 4.322141475084445,
        "y_m": 5.88772113441892,
        "heading_deg": 220.0404,
        "distance_m": 3.3249,
        "angle_deg_cw": 17.9138,
        "yaw_deg": -22.1266,
        "bearing_robot_deg_ccw": -17.91380000000001,
        "snapshot_path": "/tmp/location_front_1781596026466.jpg",
        "yaw_corrected_deg": -40.0404,
        "position_residual_m": 1.7294344386906582,
        "heading_residual_deg": 31.789634564599027,
        "weight": 0.3301005691632529
      },
      {
        "tag_id": 41,
        "camera_role": "front",
        "camera_offset_deg": 0.0,
        "camera_forward_offset_m": 0.055,
        "camera_x_m": 4.218905037953307,
        "camera_y_m": 3.6422020357345986,
        "x_m": 4.273905009773151,
        "y_m": 3.642146359740969,
        "heading_deg": 179.942,
        "distance_m": 3.0192,
        "angle_deg_cw": -0.8589,
        "yaw_deg": -0.8009,
        "bearing_robot_deg_ccw": 0.8589000000000055,
        "snapshot_path": "/tmp/location_front_1781596026466.jpg",
        "yaw_corrected_deg": 0.05800000000000005,
        "position_residual_m": 0.5257737576009373,
        "heading_residual_deg": 8.308765435400971,
        "weight": 0.5645269719073078
      },
      {
        "tag_id": 42,
        "camera_role": "front",
        "camera_offset_deg": 0.0,
        "camera_forward_offset_m": 0.055,
        "camera_x_m": 4.301322009574737,
        "camera_y_m": 3.8245724470250013,
        "x_m": 4.356294105243249,
        "y_m": 3.82632421693342,
        "heading_deg": 181.8252,
        "distance_m": 3.2976,
        "angle_deg_cw": -19.0412,
        "yaw_deg": -20.8664,
        "bearing_robot_deg_ccw": 19.041200000000003,
        "snapshot_path": "/tmp/location_front_1781596026466.jpg",
        "yaw_corrected_deg": -1.8251999999999988,
        "position_residual_m": 0.33294449015926214,
        "heading_residual_deg": 6.4255654354009835,
        "weight": 0.3176677386202515
      },
      {
        "tag_id": 43,
        "camera_role": "front",
        "camera_offset_deg": 0.0,
        "camera_forward_offset_m": 0.055,
        "camera_x_m": 4.333551422880978,
        "camera_y_m": 4.178085639666735,
        "x_m": 4.388160823102464,
        "y_m": 4.184628835174258,
        "heading_deg": 186.83249999999998,
        "distance_m": 4.0233,
        "angle_deg_cw": -32.4639,
        "yaw_deg": -39.2964,
        "bearing_robot_deg_ccw": 32.463899999999995,
        "snapshot_path": "/tmp/location_front_1781596026466.jpg",
        "yaw_corrected_deg": -6.832499999999996,
        "position_residual_m": 0.031133693939172393,
        "heading_residual_deg": 1.418265435400997,
        "weight": 0.1388860816392491
      },
      {
        "tag_id": 44,
        "camera_role": "front",
        "camera_offset_deg": 0.0,
        "camera_forward_offset_m": 0.055,
        "camera_x_m": 4.31938085081645,
        "camera_y_m": 4.6522293393117,
        "x_m": 4.373070640913211,
        "y_m": 4.66416275623083,
        "heading_deg": 192.5312,
        "distance_m": 5.0937,
        "angle_deg_cw": -39.9896,
        "yaw_deg": -52.5208,
        "bearing_robot_deg_ccw": 39.989599999999996,
        "snapshot_path": "/tmp/location_front_1781596026466.jpg",
        "yaw_corrected_deg": -12.531199999999998,
        "position_residual_m": 0.5052051644630606,
        "heading_residual_deg": 4.280434564599034,
        "weight": 0.06646217927015073
      }
    ],
    "hard_outliers": [],
    "soft_outliers": [
      {
        "tag_id": 38,
        "camera_role": "front",
        "camera_offset_deg": 0.0,
        "camera_forward_offset_m": 0.055,
        "camera_x_m": 4.711646353292452,
        "camera_y_m": 3.6062436353619685,
        "x_m": 4.766646306297523,
        "y_m": 3.6061717365439105,
        "heading_deg": 179.92510000000004,
        "distance_m": 2.6217,
        "angle_deg_cw": 37.3636,
        "yaw_deg": -52.5615,
        "bearing_robot_deg_ccw": -37.36359999999999,
        "snapshot_path": "/tmp/location_front_1781596026466.jpg",
        "yaw_corrected_deg": -89.9251,
        "position_residual_m": 0.6800605053486289,
        "heading_residual_deg": 8.325665435400936,
        "weight": 0.10480564091785488
      },
      {
        "tag_id": 39,
        "camera_role": "front",
        "camera_offset_deg": 0.0,
        "camera_forward_offset_m": 0.055,
        "camera_x_m": 4.469795260806633,
        "camera_y_m": 3.403129181725988,
        "x_m": 4.524650425458361,
        "y_m": 3.3991403333919803,
        "heading_deg": 175.841,
        "distance_m": 3.3268,
        "angle_deg_cw": 28.5328,
        "yaw_deg": -57.3082,
        "bearing_robot_deg_ccw": -28.53280000000001,
        "snapshot_path": "/tmp/location_front_1781596026466.jpg",
        "yaw_corrected_deg": -85.84100000000001,
        "position_residual_m": 0.7752954661075431,
        "heading_residual_deg": 12.40976543540097,
        "weight": 0.2006290884755269
      },
      {
        "tag_id": 40,
        "camera_role": "front",
        "camera_offset_deg": 0.0,
        "camera_forward_offset_m": 0.055,
        "camera_x_m": 4.280033969269751,
        "camera_y_m": 5.852338116542183,
        "x_m": 4.322141475084445,
        "y_m": 5.88772113441892,
        "heading_deg": 220.0404,
        "distance_m": 3.3249,
        "angle_deg_cw": 17.9138,
        "yaw_deg": -22.1266,
        "bearing_robot_deg_ccw": -17.91380000000001,
        "snapshot_path": "/tmp/location_front_1781596026466.jpg",
        "yaw_corrected_deg": -40.0404,
        "position_residual_m": 1.7294344386906582,
        "heading_residual_deg": 31.789634564599027,
        "weight": 0.3301005691632529
      },
      {
        "tag_id": 41,
        "camera_role": "front",
        "camera_offset_deg": 0.0,
        "camera_forward_offset_m": 0.055,
        "camera_x_m": 4.218905037953307,
        "camera_y_m": 3.6422020357345986,
        "x_m": 4.273905009773151,
        "y_m": 3.642146359740969,
        "heading_deg": 179.942,
        "distance_m": 3.0192,
        "angle_deg_cw": -0.8589,
        "yaw_deg": -0.8009,
        "bearing_robot_deg_ccw": 0.8589000000000055,
        "snapshot_path": "/tmp/location_front_1781596026466.jpg",
        "yaw_corrected_deg": 0.05800000000000005,
        "position_residual_m": 0.5257737576009373,
        "heading_residual_deg": 8.308765435400971,
        "weight": 0.5645269719073078
      },
      {
        "tag_id": 44,
        "camera_role": "front",
        "camera_offset_deg": 0.0,
        "camera_forward_offset_m": 0.055,
        "camera_x_m": 4.31938085081645,
        "camera_y_m": 4.6522293393117,
        "x_m": 4.373070640913211,
        "y_m": 4.66416275623083,
        "heading_deg": 192.5312,
        "distance_m": 5.0937,
        "angle_deg_cw": -39.9896,
        "yaw_deg": -52.5208,
        "bearing_robot_deg_ccw": 39.989599999999996,
        "snapshot_path": "/tmp/location_front_1781596026466.jpg",
        "yaw_corrected_deg": -12.531199999999998,
        "position_residual_m": 0.5052051644630606,
        "heading_residual_deg": 4.280434564599034,
        "weight": 0.06646217927015073
      }
    ]
  },
  "tag_diagnostics": [
    {
      "tag_id": 40,
      "camera_role": "front",
      "used_in_solution": true,
      "hard_outlier": false,
      "soft_outlier": true,
      "tag_world": {
        "x_m": 1.2,
        "y_m": 4.6,
        "yaw_deg": 0.0,
        "facing": "right"
      },
      "observed": {
        "distance_m": 3.3249,
        "angle_deg_cw": 17.9138,
        "yaw_deg": -22.1266,
        "bearing_robot_deg_ccw": -17.91380000000001,
        "camera_forward_offset_m": 0.055
      },
      "single_tag_solution": {
        "x_m": 4.322141475084445,
        "y_m": 5.88772113441892,
        "heading_deg": 220.0404,
        "camera_x_m": 4.280033969269751,
        "camera_y_m": 5.852338116542183
      },
      "residual_to_final": {
        "position_m": 1.7294344386906582,
        "heading_deg": 31.789634564599027
      },
      "weight": 0.3301005691632529,
      "snapshot_path": "/tmp/location_front_1781596026466.jpg"
    },
    {
      "tag_id": 39,
      "camera_role": "front",
      "used_in_solution": true,
      "hard_outlier": false,
      "soft_outlier": true,
      "tag_world": {
        "x_m": 1.67,
        "y_m": 5.2,
        "yaw_deg": 270.0,
        "facing": "down"
      },
      "observed": {
        "distance_m": 3.3268,
        "angle_deg_cw": 28.5328,
        "yaw_deg": -57.3082,
        "bearing_robot_deg_ccw": -28.53280000000001,
        "camera_forward_offset_m": 0.055
      },
      "single_tag_solution": {
        "x_m": 4.524650425458361,
        "y_m": 3.3991403333919803,
        "heading_deg": 175.841,
        "camera_x_m": 4.469795260806633,
        "camera_y_m": 3.403129181725988
      },
      "residual_to_final": {
        "position_m": 0.7752954661075431,
        "heading_deg": 12.40976543540097
      },
      "weight": 0.2006290884755269,
      "snapshot_path": "/tmp/location_front_1781596026466.jpg"
    },
    {
      "tag_id": 38,
      "camera_role": "front",
      "used_in_solution": true,
      "hard_outlier": false,
      "soft_outlier": true,
      "tag_world": {
        "x_m": 2.63,
        "y_m": 5.2,
        "yaw_deg": 270.0,
        "facing": "down"
      },
      "observed": {
        "distance_m": 2.6217,
        "angle_deg_cw": 37.3636,
        "yaw_deg": -52.5615,
        "bearing_robot_deg_ccw": -37.36359999999999,
        "camera_forward_offset_m": 0.055
      },
      "single_tag_solution": {
        "x_m": 4.766646306297523,
        "y_m": 3.6061717365439105,
        "heading_deg": 179.92510000000004,
        "camera_x_m": 4.711646353292452,
        "camera_y_m": 3.6062436353619685
      },
      "residual_to_final": {
        "position_m": 0.6800605053486289,
        "heading_deg": 8.325665435400936
      },
      "weight": 0.10480564091785488,
      "snapshot_path": "/tmp/location_front_1781596026466.jpg"
    },
    {
      "tag_id": 41,
      "camera_role": "front",
      "used_in_solution": true,
      "hard_outlier": false,
      "soft_outlier": true,
      "tag_world": {
        "x_m": 1.2,
        "y_m": 3.6,
        "yaw_deg": 0.0,
        "facing": "right"
      },
      "observed": {
        "distance_m": 3.0192,
        "angle_deg_cw": -0.8589,
        "yaw_deg": -0.8009,
        "bearing_robot_deg_ccw": 0.8589000000000055,
        "camera_forward_offset_m": 0.055
      },
      "single_tag_solution": {
        "x_m": 4.273905009773151,
        "y_m": 3.642146359740969,
        "heading_deg": 179.942,
        "camera_x_m": 4.218905037953307,
        "camera_y_m": 3.6422020357345986
      },
      "residual_to_final": {
        "position_m": 0.5257737576009373,
        "heading_deg": 8.308765435400971
      },
      "weight": 0.5645269719073078,
      "snapshot_path": "/tmp/location_front_1781596026466.jpg"
    },
    {
      "tag_id": 44,
      "camera_role": "front",
      "used_in_solution": true,
      "hard_outlier": false,
      "soft_outlier": true,
      "tag_world": {
        "x_m": 1.22,
        "y_m": 0.61,
        "yaw_deg": 0.0,
        "facing": "right"
      },
      "observed": {
        "distance_m": 5.0937,
        "angle_deg_cw": -39.9896,
        "yaw_deg": -52.5208,
        "bearing_robot_deg_ccw": 39.989599999999996,
        "camera_forward_offset_m": 0.055
      },
      "single_tag_solution": {
        "x_m": 4.373070640913211,
        "y_m": 4.66416275623083,
        "heading_deg": 192.5312,
        "camera_x_m": 4.31938085081645,
        "camera_y_m": 4.6522293393117
      },
      "residual_to_final": {
        "position_m": 0.5052051644630606,
        "heading_deg": 4.280434564599034
      },
      "weight": 0.06646217927015073,
      "snapshot_path": "/tmp/location_front_1781596026466.jpg"
    },
    {
      "tag_id": 42,
      "camera_role": "front",
      "used_in_solution": true,
      "hard_outlier": false,
      "soft_outlier": false,
      "tag_world": {
        "x_m": 1.22,
        "y_m": 2.65,
        "yaw_deg": 0.0,
        "facing": "right"
      },
      "observed": {
        "distance_m": 3.2976,
        "angle_deg_cw": -19.0412,
        "yaw_deg": -20.8664,
        "bearing_robot_deg_ccw": 19.041200000000003,
        "camera_forward_offset_m": 0.055
      },
      "single_tag_solution": {
        "x_m": 4.356294105243249,
        "y_m": 3.82632421693342,
        "heading_deg": 181.8252,
        "camera_x_m": 4.301322009574737,
        "camera_y_m": 3.8245724470250013
      },
      "residual_to_final": {
        "position_m": 0.33294449015926214,
        "heading_deg": 6.4255654354009835
      },
      "weight": 0.3176677386202515,
      "snapshot_path": "/tmp/location_front_1781596026466.jpg"
    },
    {
      "tag_id": 43,
      "camera_role": "front",
      "used_in_solution": true,
      "hard_outlier": false,
      "soft_outlier": false,
      "tag_world": {
        "x_m": 1.22,
        "y_m": 1.63,
        "yaw_deg": 0.0,
        "facing": "right"
      },
      "observed": {
        "distance_m": 4.0233,
        "angle_deg_cw": -32.4639,
        "yaw_deg": -39.2964,
        "bearing_robot_deg_ccw": 32.463899999999995,
        "camera_forward_offset_m": 0.055
      },
      "single_tag_solution": {
        "x_m": 4.388160823102464,
        "y_m": 4.184628835174258,
        "heading_deg": 186.83249999999998,
        "camera_x_m": 4.333551422880978,
        "camera_y_m": 4.178085639666735
      },
      "residual_to_final": {
        "position_m": 0.031133693939172393,
        "heading_deg": 1.418265435400997
      },
      "weight": 0.1388860816392491,
      "snapshot_path": "/tmp/location_front_1781596026466.jpg"
    }
  ],
  "metadata": {
    "report_time": "2026-06-16-15:47:26",
    "direct_command_stream_id": "1781596026772-0",
    "trial": "P2A-001",
    "notes": ""
  }
}