{
  "script_version": "t11_observation_only_v2_yaw_keep_flip_quant",
  "robot_id": "twin-scout-charlie",
  "ground_truth": {
    "x_m": 2.0,
    "y_m": 2.5,
    "heading_deg": 295.0
  },
  "observations": [
    {
      "tag_id": 45,
      "camera_role": "front",
      "distance_m": 2.3463,
      "angle_deg": 34.7838,
      "yaw_deg": 24.8982,
      "source": "t11_observation_only"
    },
    {
      "tag_id": 46,
      "camera_role": "front",
      "distance_m": 2.4182,
      "angle_deg": 10.2012,
      "yaw_deg": -17.6283,
      "source": "t11_observation_only"
    },
    {
      "tag_id": 47,
      "camera_role": "front",
      "distance_m": 2.8338,
      "angle_deg": -9.715,
      "yaw_deg": -33.9597,
      "source": "t11_observation_only"
    },
    {
      "tag_id": 48,
      "camera_role": "front",
      "distance_m": 3.4045,
      "angle_deg": -20.6612,
      "yaw_deg": -49.1427,
      "source": "t11_observation_only"
    },
    {
      "tag_id": 49,
      "camera_role": "front",
      "distance_m": 4.2257,
      "angle_deg": -26.1469,
      "yaw_deg": -54.5004,
      "source": "t11_observation_only"
    },
    {
      "tag_id": 39,
      "camera_role": "rear",
      "distance_m": 2.7188,
      "angle_deg": 21.2606,
      "yaw_deg": -2.3419,
      "source": "t11_observation_only"
    },
    {
      "tag_id": 41,
      "camera_role": "rear",
      "distance_m": 1.3149,
      "angle_deg": -6.5187,
      "yaw_deg": 55.3562,
      "source": "t11_observation_only"
    }
  ],
  "source_log_file": "D:\\Data\\_Action\\_RunNMS\\testLocation\\output\\t11_observation_collection\\obscheck_x2.00_y2.50_h295_20260707_153220.json",
  "report_time": "2026-07-07-15:32:19"
}